{
    "getCurrentKrsStatus": {
        "result": [
            {
                "date_from": "2001-06-28",
                "legal_form": "ZWIĄZEK ZAWODOWY",
                "name": "ZWIĄZEK ZAWODOWY PRACOWNIKÓW",
                "nip": "5673706969",
                "relation": "WSPÓLNIK",
                "relation_detailed": ""
            },
            {
                "date_from": "2001-06-28",
                "legal_form": "ZWIĄZEK ZAWODOWY",
                "name": "ZWIĄZEK ZAWODOWY PRACOWNIKÓW",
                "nip": "1246997402",
                "relation": "ZARZĄD",
                "relation_detailed": "PRZEWODNICZĄCY"
            }
        ]
    },
    "addPeselWithCeidg": {
        "msg": "success"
    },
    "removePeselWithCeidg": {
        "msg": "success"
    },
    "listPeselWithCeidg": {
        "list": [
            {
                "address_city": "Wrocław",
                "address_number": "20",
                "address_street": "Ptasia",
                "email": "email@wp.pl",
                "nip": "5673706969",
                "pesel": "80250175501",
                "phone": "500112233"
            },
            {
                "address_city": "Poznań",
                "address_number": "2a",
                "address_street": "Wielka",
                "email": "email@wro.pl",
                "nip": "1246997402",
                "pesel": "00302459672",
                "phone": "600112233"
            }
        ]
    },
    "collectCeidgChanges": {
        "items": {
            "72110894718": [
                {
                    "begin_date": "2018-06-05",
                    "nip": "6203474226",
                    "same_value": "6203474226",
                    "same_value_type": "nip"
                },
                {
                    "begin_date": "2018-06-05",
                    "nip": "2097070817",
                    "same_value": "email@wp.pl",
                    "same_value_type": "email"
                }
            ],
            "04241460461": [
                {
                    "begin_date": "2018-06-05",
                    "nip": "7181856262",
                    "same_value": "7181856262",
                    "same_value_type": "nip"
                },
                {
                    "begin_date": "2018-06-05",
                    "nip": "7181856262",
                    "same_value": "email@wp.pl",
                    "same_value_type": "email"
                }
            ],
             "04082205676": [
                {
                    "begin_date": "2018-06-05",
                    "nip": "7181856262",
                    "same_value": "7181856262",
                    "same_value_type": "nip"
                },
                {
                    "begin_date": "2018-06-05",
                    "nip": "7181856262",
                    "same_value": "email@wp.pl",
                    "same_value_type": "email"
                }
            ]
        }
    }
}









